opsgenie/__init__.py
opsgenie/api/__init__.py
opsgenie/api/v2.py
opsgenie_python_api-0.2.dist-info/LICENSE
opsgenie_python_api-0.2.dist-info/METADATA
opsgenie_python_api-0.2.dist-info/WHEEL
opsgenie_python_api-0.2.dist-info/top_level.txt
opsgenie_python_api-0.2.dist-info/RECORD
