Metadata-Version: 2.1
Name: opsgenie-python-api
Version: 0.2
Summary: Python bindings for Opsgenie API
Home-page: https://github.com/stanislavulrych/opsgenie-python-api
Author: Stanislav Ulrych
Author-email: stanislav.ulrych@gmail.com
Project-URL: Bug Tracker, https://github.com/stanislavulrych/opsgenie-python-api/issues
Classifier: Programming Language :: Python :: 3
Classifier: License :: OSI Approved :: Apache Software License
Classifier: Operating System :: OS Independent
Requires-Python: >=3.10.11
License-File: LICENSE
